{
    "REGISTRY_ADDRESS" : "0x5FbDB2315678afecb367f032d93F642f64180aa3",
    "TOKEN_ADDRESS" : "0xe7f1725E7734CE288F8367e1Bb143E90bb3F0512",
    "MARKETPLACE_ADDRESS" : "0x9fE46736679d2D9a65F0992F2272dE9f3c7fa6e0",

    "Hoodi_REGISTRY_ADDRESS" : "0x0f2B864BA13573C7385EB8501141D05B5d1D8B21",
    "Hoodi_TOKEN_ADDRESS" : "0x6800Ac0f2f4Da459EdEd89105cfcfDB54ADB34cD",
    "Hoodi_MARKETPLACE_ADDRESS" : "0x496107c34f0d0fa85EaA023467628CeFe69366B1",

    "ProducerRegistryABI": [
    {
      "inputs": [],
      "stateMutability": "nonpayable",
      "type": "constructor"
    },
    {
      "anonymous": false,
      "inputs": [
        {
          "indexed": false,
          "internalType": "address",
          "name": "producer",
          "type": "address"
        }
      ],
      "name": "ProducerApproved",
      "type": "event"
    },
    {
      "anonymous": false,
      "inputs": [
        {
          "indexed": false,
          "internalType": "address",
          "name": "producer",
          "type": "address"
        }
      ],
      "name": "ProducerRejected",
      "type": "event"
    },
    {
      "anonymous": false,
      "inputs": [
        {
          "indexed": false,
          "internalType": "address",
          "name": "producer",
          "type": "address"
        }
      ],
      "name": "ProducerRequested",
      "type": "event"
    },
    {
      "inputs": [],
      "name": "admin",
      "outputs": [
        {
          "internalType": "address",
          "name": "",
          "type": "address"
        }
      ],
      "stateMutability": "view",
      "type": "function"
    },
    {
      "inputs": [
        {
          "internalType": "uint256",
          "name": "",
          "type": "uint256"
        }
      ],
      "name": "allProducers",
      "outputs": [
        {
          "internalType": "address",
          "name": "",
          "type": "address"
        }
      ],
      "stateMutability": "view",
      "type": "function"
    },
    {
      "inputs": [
        {
          "internalType": "address",
          "name": "producer",
          "type": "address"
        }
      ],
      "name": "approveProducer",
      "outputs": [],
      "stateMutability": "nonpayable",
      "type": "function"
    },
    {
      "inputs": [],
      "name": "getAllProducers",
      "outputs": [
        {
          "internalType": "address[]",
          "name": "",
          "type": "address[]"
        }
      ],
      "stateMutability": "view",
      "type": "function"
    },
    {
      "inputs": [],
      "name": "getPendingProducers",
      "outputs": [
        {
          "internalType": "address[]",
          "name": "",
          "type": "address[]"
        }
      ],
      "stateMutability": "view",
      "type": "function"
    },
    {
      "inputs": [
        {
          "internalType": "address",
          "name": "producer",
          "type": "address"
        }
      ],
      "name": "getProducerDetails",
      "outputs": [
        {
          "internalType": "string",
          "name": "",
          "type": "string"
        },
        {
          "internalType": "string",
          "name": "",
          "type": "string"
        },
        {
          "internalType": "uint256",
          "name": "",
          "type": "uint256"
        },
        {
          "internalType": "string",
          "name": "",
          "type": "string"
        },
        {
          "internalType": "enum ProducerRegistry.Status",
          "name": "",
          "type": "uint8"
        }
      ],
      "stateMutability": "view",
      "type": "function"
    },
    {
      "inputs": [
        {
          "internalType": "address",
          "name": "",
          "type": "address"
        }
      ],
      "name": "hasRequested",
      "outputs": [
        {
          "internalType": "bool",
          "name": "",
          "type": "bool"
        }
      ],
      "stateMutability": "view",
      "type": "function"
    },
    {
      "inputs": [
        {
          "internalType": "address",
          "name": "producer",
          "type": "address"
        }
      ],
      "name": "isApprovedProducer",
      "outputs": [
        {
          "internalType": "bool",
          "name": "",
          "type": "bool"
        }
      ],
      "stateMutability": "view",
      "type": "function"
    },
    {
      "inputs": [
        {
          "internalType": "uint256",
          "name": "",
          "type": "uint256"
        }
      ],
      "name": "pendingProducers",
      "outputs": [
        {
          "internalType": "address",
          "name": "",
          "type": "address"
        }
      ],
      "stateMutability": "view",
      "type": "function"
    },
    {
      "inputs": [
        {
          "internalType": "address",
          "name": "",
          "type": "address"
        }
      ],
      "name": "producers",
      "outputs": [
        {
          "internalType": "string",
          "name": "name",
          "type": "string"
        },
        {
          "internalType": "string",
          "name": "location",
          "type": "string"
        },
        {
          "internalType": "uint256",
          "name": "capacity",
          "type": "uint256"
        },
        {
          "internalType": "string",
          "name": "aadhaarHash",
          "type": "string"
        },
        {
          "internalType": "enum ProducerRegistry.Status",
          "name": "status",
          "type": "uint8"
        }
      ],
      "stateMutability": "view",
      "type": "function"
    },
    {
      "inputs": [
        {
          "internalType": "address",
          "name": "producer",
          "type": "address"
        }
      ],
      "name": "rejectProducer",
      "outputs": [],
      "stateMutability": "nonpayable",
      "type": "function"
    },
    {
      "inputs": [
        {
          "internalType": "string",
          "name": "_name",
          "type": "string"
        },
        {
          "internalType": "string",
          "name": "_location",
          "type": "string"
        },
        {
          "internalType": "uint256",
          "name": "_capacity",
          "type": "uint256"
        },
        {
          "internalType": "string",
          "name": "_aadhaarHash",
          "type": "string"
        }
      ],
      "name": "requestProducerApproval",
      "outputs": [],
      "stateMutability": "nonpayable",
      "type": "function"
    }
  ],
  "EnergyTokenABI": [
    {
      "inputs": [
        {
          "internalType": "address",
          "name": "registryAddress",
          "type": "address"
        }
      ],
      "stateMutability": "nonpayable",
      "type": "constructor"
    },
    {
      "inputs": [
        {
          "internalType": "address",
          "name": "spender",
          "type": "address"
        },
        {
          "internalType": "uint256",
          "name": "allowance",
          "type": "uint256"
        },
        {
          "internalType": "uint256",
          "name": "needed",
          "type": "uint256"
        }
      ],
      "name": "ERC20InsufficientAllowance",
      "type": "error"
    },
    {
      "inputs": [
        {
          "internalType": "address",
          "name": "sender",
          "type": "address"
        },
        {
          "internalType": "uint256",
          "name": "balance",
          "type": "uint256"
        },
        {
          "internalType": "uint256",
          "name": "needed",
          "type": "uint256"
        }
      ],
      "name": "ERC20InsufficientBalance",
      "type": "error"
    },
    {
      "inputs": [
        {
          "internalType": "address",
          "name": "approver",
          "type": "address"
        }
      ],
      "name": "ERC20InvalidApprover",
      "type": "error"
    },
    {
      "inputs": [
        {
          "internalType": "address",
          "name": "receiver",
          "type": "address"
        }
      ],
      "name": "ERC20InvalidReceiver",
      "type": "error"
    },
    {
      "inputs": [
        {
          "internalType": "address",
          "name": "sender",
          "type": "address"
        }
      ],
      "name": "ERC20InvalidSender",
      "type": "error"
    },
    {
      "inputs": [
        {
          "internalType": "address",
          "name": "spender",
          "type": "address"
        }
      ],
      "name": "ERC20InvalidSpender",
      "type": "error"
    },
    {
      "anonymous": false,
      "inputs": [
        {
          "indexed": true,
          "internalType": "address",
          "name": "owner",
          "type": "address"
        },
        {
          "indexed": true,
          "internalType": "address",
          "name": "spender",
          "type": "address"
        },
        {
          "indexed": false,
          "internalType": "uint256",
          "name": "value",
          "type": "uint256"
        }
      ],
      "name": "Approval",
      "type": "event"
    },
    {
      "anonymous": false,
      "inputs": [
        {
          "indexed": true,
          "internalType": "address",
          "name": "from",
          "type": "address"
        },
        {
          "indexed": true,
          "internalType": "address",
          "name": "to",
          "type": "address"
        },
        {
          "indexed": false,
          "internalType": "uint256",
          "name": "value",
          "type": "uint256"
        }
      ],
      "name": "Transfer",
      "type": "event"
    },
    {
      "inputs": [
        {
          "internalType": "address",
          "name": "owner",
          "type": "address"
        },
        {
          "internalType": "address",
          "name": "spender",
          "type": "address"
        }
      ],
      "name": "allowance",
      "outputs": [
        {
          "internalType": "uint256",
          "name": "",
          "type": "uint256"
        }
      ],
      "stateMutability": "view",
      "type": "function"
    },
    {
      "inputs": [
        {
          "internalType": "address",
          "name": "spender",
          "type": "address"
        },
        {
          "internalType": "uint256",
          "name": "value",
          "type": "uint256"
        }
      ],
      "name": "approve",
      "outputs": [
        {
          "internalType": "bool",
          "name": "",
          "type": "bool"
        }
      ],
      "stateMutability": "nonpayable",
      "type": "function"
    },
    {
      "inputs": [
        {
          "internalType": "address",
          "name": "account",
          "type": "address"
        }
      ],
      "name": "balanceOf",
      "outputs": [
        {
          "internalType": "uint256",
          "name": "",
          "type": "uint256"
        }
      ],
      "stateMutability": "view",
      "type": "function"
    },
    {
      "inputs": [],
      "name": "decimals",
      "outputs": [
        {
          "internalType": "uint8",
          "name": "",
          "type": "uint8"
        }
      ],
      "stateMutability": "view",
      "type": "function"
    },
    {
      "inputs": [
        {
          "internalType": "uint256",
          "name": "amount",
          "type": "uint256"
        }
      ],
      "name": "mintEnergy",
      "outputs": [],
      "stateMutability": "nonpayable",
      "type": "function"
    },
    {
      "inputs": [],
      "name": "name",
      "outputs": [
        {
          "internalType": "string",
          "name": "",
          "type": "string"
        }
      ],
      "stateMutability": "view",
      "type": "function"
    },
    {
      "inputs": [],
      "name": "registry",
      "outputs": [
        {
          "internalType": "contract IProducerRegistry",
          "name": "",
          "type": "address"
        }
      ],
      "stateMutability": "view",
      "type": "function"
    },
    {
      "inputs": [],
      "name": "symbol",
      "outputs": [
        {
          "internalType": "string",
          "name": "",
          "type": "string"
        }
      ],
      "stateMutability": "view",
      "type": "function"
    },
    {
      "inputs": [],
      "name": "totalSupply",
      "outputs": [
        {
          "internalType": "uint256",
          "name": "",
          "type": "uint256"
        }
      ],
      "stateMutability": "view",
      "type": "function"
    },
    {
      "inputs": [
        {
          "internalType": "address",
          "name": "to",
          "type": "address"
        },
        {
          "internalType": "uint256",
          "name": "value",
          "type": "uint256"
        }
      ],
      "name": "transfer",
      "outputs": [
        {
          "internalType": "bool",
          "name": "",
          "type": "bool"
        }
      ],
      "stateMutability": "nonpayable",
      "type": "function"
    },
    {
      "inputs": [
        {
          "internalType": "address",
          "name": "from",
          "type": "address"
        },
        {
          "internalType": "address",
          "name": "to",
          "type": "address"
        },
        {
          "internalType": "uint256",
          "name": "value",
          "type": "uint256"
        }
      ],
      "name": "transferFrom",
      "outputs": [
        {
          "internalType": "bool",
          "name": "",
          "type": "bool"
        }
      ],
      "stateMutability": "nonpayable",
      "type": "function"
    }
  ],
  "EnergyMarketplaceABI": [
    {
      "inputs": [
        {
          "internalType": "address",
          "name": "registryAddress",
          "type": "address"
        },
        {
          "internalType": "address",
          "name": "tokenAddress",
          "type": "address"
        }
      ],
      "stateMutability": "nonpayable",
      "type": "constructor"
    },
    {
      "anonymous": false,
      "inputs": [
        {
          "indexed": true,
          "internalType": "uint256",
          "name": "listingId",
          "type": "uint256"
        },
        {
          "indexed": true,
          "internalType": "address",
          "name": "producer",
          "type": "address"
        },
        {
          "indexed": false,
          "internalType": "uint256",
          "name": "amount",
          "type": "uint256"
        },
        {
          "indexed": false,
          "internalType": "uint256",
          "name": "price",
          "type": "uint256"
        }
      ],
      "name": "EnergyListed",
      "type": "event"
    },
    {
      "anonymous": false,
      "inputs": [
        {
          "indexed": true,
          "internalType": "uint256",
          "name": "listingId",
          "type": "uint256"
        },
        {
          "indexed": true,
          "internalType": "address",
          "name": "buyer",
          "type": "address"
        },
        {
          "indexed": false,
          "internalType": "uint256",
          "name": "amount",
          "type": "uint256"
        },
        {
          "indexed": false,
          "internalType": "uint256",
          "name": "totalCost",
          "type": "uint256"
        }
      ],
      "name": "EnergyPurchased",
      "type": "event"
    },
    {
      "inputs": [
        {
          "internalType": "uint256",
          "name": "listingId",
          "type": "uint256"
        },
        {
          "internalType": "uint256",
          "name": "_amt",
          "type": "uint256"
        }
      ],
      "name": "buyEnergy",
      "outputs": [],
      "stateMutability": "payable",
      "type": "function"
    },
    {
      "inputs": [
        {
          "internalType": "uint256",
          "name": "_amt",
          "type": "uint256"
        },
        {
          "internalType": "uint256",
          "name": "_price",
          "type": "uint256"
        }
      ],
      "name": "listEnergy",
      "outputs": [],
      "stateMutability": "nonpayable",
      "type": "function"
    },
    {
      "inputs": [],
      "name": "listingCount",
      "outputs": [
        {
          "internalType": "uint256",
          "name": "",
          "type": "uint256"
        }
      ],
      "stateMutability": "view",
      "type": "function"
    },
    {
      "inputs": [
        {
          "internalType": "uint256",
          "name": "",
          "type": "uint256"
        }
      ],
      "name": "listings",
      "outputs": [
        {
          "internalType": "address",
          "name": "producer",
          "type": "address"
        },
        {
          "internalType": "uint256",
          "name": "amount",
          "type": "uint256"
        },
        {
          "internalType": "uint256",
          "name": "price",
          "type": "uint256"
        },
        {
          "internalType": "bool",
          "name": "active",
          "type": "bool"
        }
      ],
      "stateMutability": "view",
      "type": "function"
    },
    {
      "inputs": [],
      "name": "registry",
      "outputs": [
        {
          "internalType": "contract IProducerRegistry",
          "name": "",
          "type": "address"
        }
      ],
      "stateMutability": "view",
      "type": "function"
    },
    {
      "inputs": [],
      "name": "token",
      "outputs": [
        {
          "internalType": "contract IEnergyToken",
          "name": "",
          "type": "address"
        }
      ],
      "stateMutability": "view",
      "type": "function"
    }
  ]
}